{"code":0,"message":"","data":{"list":[{"_id":"6071b8f1a21eca0f48075995","uid":95084,"courseid":21,"sectionid":29,"eid":118037,"note":"低压槽线吧，线总是长的吧","updated_at":"2021-04-10 22:40:54","created_at":"2021-04-10 22:40:49","approve":{"95084":95084},"number":1,"sum_number":1,"isapprove":false,"isoppose":false,"nickname":"你认识飞院的帅民哥吗","avatar":"http://resource.feizhiyi.com/fzy/Uploads/Attachment/20210418/95084_43828_small.jpg","oppose_number":0},{"_id":"5fcb34e5f8945f3e6f2561f3","uid":95206,"courseid":21,"sectionid":29,"eid":118037,"note":"罗景 永远的神","is_train":true,"taskid":816,"updated_at":"2021-03-10 09:25:24","created_at":"2020-12-05 15:21:09","approve":{"90044":90044,"95206":95206},"number":2,"oppose":{"75108":75108},"oppose_number":1,"sum_number":1,"isapprove":false,"isoppose":false,"nickname":"对方正在输入...","avatar":"http://resource.feizhiyi.com/fzy/Uploads/Attachment/20200907/95206_72885_small.jpg"},{"_id":"5fcb3081267561768e507d9a","uid":95071,"courseid":21,"sectionid":29,"eid":118037,"note":"我罗景必开飞机","updated_at":"2020-12-29 13:39:54","created_at":"2020-12-05 15:02:25","approve":{"95071":95071,"95206":95206},"number":2,"oppose":{"75108":75108},"oppose_number":1,"sum_number":1,"isapprove":false,"isoppose":false,"nickname":"403SUP","avatar":"http://resource.feizhiyi.com/fzy/Uploads/Attachment/20201114/95071_53016_small.jpg"},{"_id":"605b1e5d57dce970593e0f46","uid":85945,"courseid":21,"sectionid":29,"eid":118037,"note":"低压流出来的下场，区域是低压槽","is_train":true,"taskid":816,"updated_at":"2021-03-24 19:11:25","created_at":"2021-03-24 19:11:25","sum_number":0,"isapprove":false,"isoppose":false,"nickname":"快落小徐","avatar":"http://resource.feizhiyi.com/fzy/Uploads/Attachment/20210408/85945_15663_small.jpg","number":0,"oppose_number":0}],"total":4}}