{"code":0,"message":"","data":{"list":[{"_id":"5ee6493540fecb683c29aab2","uid":88214,"courseid":20,"sectionid":1,"eid":20936,"note":"公安警察归国家","updated_at":"2020-09-02 14:51:22","created_at":"2020-06-14 23:58:45","number":2,"approve":{"86850":86850,"88214":88214},"sum_number":2,"isapprove":false,"isoppose":false,"nickname":"爱抽华子的李会长","avatar":"http://resource.feizhiyi.com/fzy/Uploads/Attachment/20200717/88214_36431_small.jpg","oppose_number":0},{"_id":"5fc06a5f7bf3d37b5c3893d2","uid":93447,"courseid":20,"sectionid":1,"eid":20936,"note":"公安警察归国家","updated_at":"2021-01-15 12:14:27","created_at":"2020-11-27 10:54:23","approve":{"68902":68902},"number":1,"sum_number":1,"isapprove":false,"isoppose":false,"nickname":"Jahseh","avatar":"http://resource.feizhiyi.com/fzy/Uploads/Attachment/20200928/93447_61310_small.jpg","oppose_number":0},{"_id":"5c71001c40fecb324667f24c","uid":72770,"courseid":20,"sectionid":1,"eid":20936,"note":"公安警察归国家","updated_at":"2020-01-02 11:13:02","created_at":"2019-02-23 16:11:08","number":1,"approve":{"72648":72648},"sum_number":1,"isapprove":false,"isoppose":false,"nickname":"libertine","avatar":"http://resource.feizhiyi.com/fzy/Uploads/Attachment/20190221/72770_67328_small.jpg","oppose_number":0},{"_id":"6049d883eda09235c8099cb4","uid":95667,"courseid":20,"sectionid":1,"eid":20936,"note":"公安警察归国家","updated_at":"2021-03-11 16:44:51","created_at":"2021-03-11 16:44:51","sum_number":0,"isapprove":false,"isoppose":false,"nickname":"breakaleg","avatar":"http://resource.feizhiyi.com/fzy/Uploads/Attachment/20200914/95667_29181_small.jpg","number":0,"oppose_number":0},{"_id":"60422e100b2d1c10830c2657","uid":94049,"courseid":20,"sectionid":1,"eid":20936,"note":"公安警察归国家","updated_at":"2021-03-05 21:11:44","created_at":"2021-03-05 21:11:44","sum_number":0,"isapprove":false,"isoppose":false,"nickname":"暴打向文潇","avatar":"http://resource.feizhiyi.com/fzy/Uploads/Attachment/20210414/94049_25307_small.jpg","number":0,"oppose_number":0},{"_id":"603c3c6a9195ad6c761a72c1","uid":98705,"courseid":20,"sectionid":1,"eid":20936,"note":"军事海关警察！","updated_at":"2021-03-01 08:59:22","created_at":"2021-03-01 08:59:22","sum_number":0,"isapprove":false,"isoppose":false,"nickname":"洛神","avatar":"http://resource.feizhiyi.com/fzy/Uploads/Attachment/20210218/98705_53863_small.jpg","number":0,"oppose_number":0},{"_id":"602f6d1819f5bc43c0097339","uid":88811,"courseid":20,"sectionid":1,"eid":20936,"note":"公安警察归国家","updated_at":"2021-02-19 15:47:36","created_at":"2021-02-19 15:47:36","sum_number":0,"isapprove":false,"isoppose":false,"nickname":"ChouTouFu","avatar":"http://resource.feizhiyi.com/fzy/Uploads/Attachment/20210126/88811_51704_small.jpg","number":0,"oppose_number":0},{"_id":"6023e6710ace1b452d58f9f7","uid":100720,"courseid":20,"sectionid":1,"eid":20936,"note":"公安警察归国家","updated_at":"2021-02-10 21:58:09","created_at":"2021-02-10 21:58:09","sum_number":0,"isapprove":false,"isoppose":false,"nickname":"龍","avatar":"http://resource.feizhiyi.com/fzy/Uploads/Attachment/20210208/100720_40248_small.jpg","number":0,"oppose_number":0},{"_id":"5fe0290f30d69400175e03a8","uid":98551,"courseid":20,"sectionid":1,"eid":20936,"note":"军事，海关，警察","updated_at":"2020-12-21 12:48:15","created_at":"2020-12-21 12:48:15","sum_number":0,"isapprove":false,"isoppose":false,"nickname":"童年的纸飞机","avatar":"http://resource.feizhiyi.com/fzy/Uploads/Attachment/20201109/98551_49364_small.jpg","number":0,"oppose_number":0},{"_id":"5f9caf8fb48e8a7f3c0aed9d","uid":95317,"courseid":20,"sectionid":1,"eid":20936,"note":"公安警察归国家","updated_at":"2020-10-31 08:27:59","created_at":"2020-10-31 08:27:59","sum_number":0,"isapprove":false,"isoppose":false,"nickname":"无法坠入爱河","avatar":"http://resource.feizhiyi.com/fzy/Uploads/Attachment/20210303/95317_22415_small.jpg","number":0,"oppose_number":0},{"_id":"5f7fc8058971433ecc47c748","uid":91349,"courseid":20,"sectionid":1,"eid":20936,"note":"公安警察 国家航空器","updated_at":"2020-10-09 10:16:37","created_at":"2020-10-09 10:16:37","sum_number":0,"isapprove":false,"isoppose":false,"nickname":"一次过","avatar":"http://resource.feizhiyi.com/fzy/Uploads/Attachment/20201127/91349_94816_small.jpg","number":0,"oppose_number":0},{"_id":"5f6845666533be2d5a3807fd","uid":94330,"courseid":20,"sectionid":1,"eid":20936,"note":"国家的","updated_at":"2020-09-21 14:17:10","created_at":"2020-09-21 14:17:10","sum_number":0,"isapprove":false,"isoppose":false,"nickname":"好运必过理论","avatar":"http://resource.feizhiyi.com/fzy/Uploads/Attachment/20200920/94330_53851_small.jpg","number":0,"oppose_number":0},{"_id":"5f49109a1033b7747c1b346e","uid":93819,"courseid":20,"sectionid":1,"eid":20936,"note":"公安警察归国家","updated_at":"2020-08-28 22:11:38","created_at":"2020-08-28 22:11:38","sum_number":0,"isapprove":false,"isoppose":false,"nickname":"NCM2WB9K","avatar":"http://resource.feizhiyi.com/fzy/themes/default/img/no-img.jpg","number":0,"oppose_number":0},{"_id":"5ef988be40fecb0434151949","uid":91019,"courseid":20,"sectionid":1,"eid":20936,"note":"公安警察归国家","updated_at":"2020-06-29 14:22:54","created_at":"2020-06-29 14:22:54","sum_number":0,"isapprove":false,"isoppose":false,"nickname":"Whale red","avatar":"http://resource.feizhiyi.com/fzy/Uploads/Attachment/20200624/91019_43853_small.jpg","number":0,"oppose_number":0},{"_id":"5ee07d2e40fecb37d527106b","uid":90167,"courseid":20,"sectionid":1,"eid":20936,"note":"公安警察归国家","updated_at":"2020-06-10 14:26:54","created_at":"2020-06-10 14:26:54","sum_number":0,"isapprove":false,"isoppose":false,"nickname":"打灰机","avatar":"http://resource.feizhiyi.com/fzy/Uploads/Attachment/20200610/90167_72736_small.jpg","number":0,"oppose_number":0},{"_id":"5ec3ce5940fecb1d5f75ffcc","uid":89264,"courseid":20,"sectionid":1,"eid":20936,"note":"公安警察归国家","updated_at":"2020-05-19 20:17:29","created_at":"2020-05-19 20:17:29","sum_number":0,"isapprove":false,"isoppose":false,"nickname":"啊啊啊啊这这这我不会","avatar":"http://resource.feizhiyi.com/fzy/Uploads/Attachment/20200712/89264_89150_small.jpg","number":0,"oppose_number":0},{"_id":"5eb90d0f40fecb171642a15f","uid":88221,"courseid":20,"sectionid":1,"eid":20936,"note":"公安 警察归国家","updated_at":"2020-05-11 16:30:07","created_at":"2020-05-11 16:30:07","sum_number":0,"isapprove":false,"isoppose":false,"nickname":"","avatar":"http://resource.feizhiyi.com/fzy/Uploads/Attachment/20200709/88221_76821_small.jpg","number":0,"oppose_number":0},{"_id":"5e268cbe40fecb702d485a3b","uid":78782,"courseid":20,"sectionid":1,"eid":20936,"note":"航空器公安警察属国家","updated_at":"2020-01-21 13:31:42","created_at":"2020-01-21 13:31:42","sum_number":0,"isapprove":false,"isoppose":false,"nickname":"FX103456","avatar":"http://resource.feizhiyi.com/fzy/Uploads/Attachment/20201227/78782_21897_small.jpg","number":0,"oppose_number":0},{"_id":"5d9c4f7740fecb769930ab60","uid":75937,"courseid":20,"sectionid":1,"eid":20936,"note":"公安 警察归国家","updated_at":"2019-10-08 16:57:27","created_at":"2019-10-08 16:57:27","sum_number":0,"isapprove":false,"isoppose":false,"nickname":"YZ","avatar":"http://resource.feizhiyi.com/fzy/Uploads/Attachment/20190721/75937_38277_small.jpg","number":0,"oppose_number":0},{"_id":"5d6e235140fecb7da84ffe94","uid":76564,"courseid":20,"sectionid":1,"eid":20936,"note":"公安警察归国家","updated_at":"2019-09-03 16:24:49","created_at":"2019-09-03 16:24:49","sum_number":0,"isapprove":false,"isoppose":false,"nickname":"无奈紫馒头","avatar":"http://resource.feizhiyi.com/fzy/Uploads/Attachment/20200930/76564_56848_small.jpg","number":0,"oppose_number":0},{"_id":"5d6b9d4140fecb61270427b2","uid":77692,"courseid":20,"sectionid":1,"eid":20936,"note":"公安警察归国家","updated_at":"2019-09-01 18:28:17","created_at":"2019-09-01 18:28:17","sum_number":0,"isapprove":false,"isoppose":false,"nickname":"14号必过","avatar":"http://resource.feizhiyi.com/fzy/Uploads/Attachment/20191110/77692_21056_small.jpg","number":0,"oppose_number":0},{"_id":"5d660d7140fecb34ea047422","uid":80303,"courseid":20,"sectionid":1,"eid":20936,"note":"公安 警察是国家航空器","updated_at":"2019-08-28 13:13:21","created_at":"2019-08-28 13:13:21","sum_number":0,"isapprove":false,"isoppose":false,"nickname":"H.Fu","avatar":"http://resource.feizhiyi.com/fzy/Uploads/Attachment/20190826/80303_99707_small.jpg","number":0,"oppose_number":0},{"_id":"5d52dafc40fecb56e159f0ef","uid":74629,"courseid":20,"sectionid":1,"eid":20936,"note":"公安和警察的区别是什么？为什么能打顿号","updated_at":"2019-08-13 23:45:00","created_at":"2019-08-13 23:45:00","sum_number":0,"isapprove":false,"isoppose":false,"nickname":"翔宇张火星","avatar":"http://resource.feizhiyi.com/fzy/Uploads/Attachment/20190916/74629_79480_small.jpg","number":0,"oppose_number":0},{"_id":"5d382ce340fecb1d3b6bbd83","uid":77139,"courseid":20,"sectionid":1,"eid":20936,"note":"国家航空器就是民用航空器踢出来的","updated_at":"2019-07-24 18:03:15","created_at":"2019-07-24 18:03:15","sum_number":0,"isapprove":false,"isoppose":false,"nickname":"TTT","avatar":"http://resource.feizhiyi.com/fzy/Uploads/Attachment/20191025/77139_60175_small.jpg","number":0,"oppose_number":0},{"_id":"5ca3137f40fecb416232c29d","uid":75029,"courseid":20,"sectionid":1,"eid":20936,"note":"公安，警察归国家","updated_at":"2019-04-02 15:47:11","created_at":"2019-04-02 15:47:11","sum_number":0,"isapprove":false,"isoppose":false,"nickname":"FXI16USW","avatar":"http://resource.feizhiyi.com/fzy/themes/default/img/no-img.jpg","number":0,"oppose_number":0},{"_id":"5bea749140fecb19903970a2","uid":64181,"courseid":20,"sectionid":1,"eid":20936,"note":"公安警察归国家","updated_at":"2018-11-13 14:52:01","created_at":"2018-11-13 14:52:01","sum_number":0,"isapprove":false,"isoppose":false,"nickname":"必须过的考试","avatar":"http://resource.feizhiyi.com/fzy/themes/default/img/no-img.jpg","number":0,"oppose_number":0},{"_id":"5b63273540fecb5e891b0397","uid":64107,"courseid":20,"sectionid":1,"eid":20936,"note":"国家航空器","updated_at":"2018-08-02 23:45:57","created_at":"2018-08-02 23:45:57","sum_number":0,"isapprove":false,"isoppose":false,"nickname":"NCZ5MBQQ","avatar":"http://resource.feizhiyi.com/fzy/themes/default/img/no-img.jpg","number":0,"oppose_number":0},{"_id":"5a74b5b840fecb1d493dcc56","uid":54833,"courseid":20,"sectionid":1,"eid":20936,"note":"国家航空器 军事海关警察","created_at":"2018-01-11 23:00:54","updated_at":"2018-01-11 23:00:54","sum_number":0,"isapprove":false,"isoppose":false,"nickname":"Shirly哒哒哒","avatar":"http://resource.feizhiyi.com/fzy/Uploads/Attachment/20180311/54833_small.jpg","number":0,"oppose_number":0},{"_id":"5a74b59e40fecb1d49391495","uid":44412,"courseid":20,"sectionid":1,"eid":20936,"note":"日","created_at":"2017-04-19 19:39:21","updated_at":"2017-11-06 20:16:38","sum_number":0,"isapprove":false,"isoppose":false,"nickname":"FXN551J","avatar":"http://resource.feizhiyi.com/fzy/Uploads/Attachment/20171031/44412_small.jpg","number":0,"oppose_number":0},{"_id":"5a74b5a840fecb1d493b01ee","uid":45611,"courseid":20,"sectionid":1,"eid":20936,"note":"军警不一体","created_at":"2017-08-25 09:25:52","updated_at":"2017-08-25 09:25:52","sum_number":0,"isapprove":false,"isoppose":false,"nickname":"Eric","avatar":"http://resource.feizhiyi.com/fzy/Uploads/Attachment/20170815/45611_small.jpg","number":0,"oppose_number":0},{"_id":"5a74b59840fecb1d4937f90c","uid":40686,"courseid":20,"sectionid":1,"eid":20936,"note":"军警不是一体","created_at":"2017-03-01 18:51:48","updated_at":"2017-03-10 21:59:28","sum_number":0,"isapprove":false,"isoppose":false,"nickname":"衬i","avatar":"http://resource.feizhiyi.com/fzy/Uploads/Attachment/20170302/40686_small.jpg","number":0,"oppose_number":0},{"_id":"5a74b59240fecb1d4936b4d3","uid":35670,"courseid":20,"sectionid":1,"eid":20936,"note":"国家的。军用不包括警察啊","created_at":"2016-10-31 12:38:17","updated_at":"2016-10-31 12:38:17","sum_number":0,"isapprove":false,"isoppose":false,"nickname":"我只能呵呵","avatar":"http://resource.feizhiyi.com/fzy/Uploads/Attachment/20181019/35670_small.jpg","number":0,"oppose_number":0},{"_id":"5a74b59240fecb1d493679c8","uid":37806,"courseid":20,"sectionid":1,"eid":20936,"note":"归国家的，第二个沙发","created_at":"2016-10-14 16:04:32","updated_at":"2016-10-14 16:04:32","sum_number":0,"isapprove":false,"isoppose":false,"nickname":"森七@","avatar":"http://resource.feizhiyi.com/fzy/Uploads/Attachment/20161011/37806_small.jpg","number":0,"oppose_number":0},{"_id":"5a74b58f40fecb1d4935edae","uid":35871,"courseid":20,"sectionid":1,"eid":20936,"note":"沙发走一个。","created_at":"2016-09-18 19:45:27","updated_at":"2016-09-18 19:45:27","sum_number":0,"isapprove":false,"isoppose":false,"nickname":"航线 ICAO一次过","avatar":"http://resource.feizhiyi.com/fzy/Uploads/Attachment/20160901/35871_small.jpg","number":0,"oppose_number":0}],"total":34}}