{"code":0,"message":"","data":{"list":[{"_id":"5da8110d40fecb45ad231d61","uid":81948,"courseid":20,"sectionid":5,"eid":9785,"note":"与飞机运动方向相反","updated_at":"2021-03-18 20:50:25","created_at":"2019-10-17 14:58:21","number":6,"approve":{"67620":67620,"80418":80418,"84065":84065,"86553":86553,"86850":86850,"96873":96873},"sum_number":6,"isapprove":false,"isoppose":false,"nickname":"March Bird","avatar":"http://resource.feizhiyi.com/fzy/Uploads/Attachment/20191017/81948_32741_small.jpg","oppose_number":0},{"_id":"5bdfe7a340fecb7b3b214b85","uid":66742,"courseid":20,"sectionid":5,"eid":9785,"note":"看错了，飞机上升","updated_at":"2020-10-17 00:17:21","created_at":"2018-11-05 14:48:03","number":4,"approve":{"64321":64321,"75004":75004,"87052":87052,"96873":96873},"sum_number":4,"isapprove":false,"isoppose":false,"nickname":"每天10块钱 文殊菩萨保佑 嗡哈喇巴扎拉","avatar":"http://resource.feizhiyi.com/fzy/Uploads/Attachment/20181008/66742_small.jpg","oppose_number":0},{"_id":"5a74b58240fecb1d493326c2","uid":24429,"courseid":20,"sectionid":5,"eid":9785,"note":"相对气流与飞机速度方向相反","created_at":"2015-12-11 17:08:09","updated_at":"2019-05-24 13:31:53","number":1,"approve":{"53808":53808},"sum_number":1,"isapprove":false,"isoppose":false,"nickname":"zhuning","avatar":"http://resource.feizhiyi.com/fzy/themes/default/img/no-img.jpg","oppose_number":0},{"_id":"5cd0513a40fecb2e8c1d9ba8","uid":76098,"courseid":20,"sectionid":5,"eid":9785,"note":"相对气流方向和飞机运动方向相反","updated_at":"2019-05-24 13:31:31","created_at":"2019-05-06 23:22:34","number":1,"approve":{"53808":53808},"sum_number":1,"isapprove":false,"isoppose":false,"nickname":"皓翔","avatar":"http://resource.feizhiyi.com/fzy/Uploads/Attachment/20190419/76098_44519_small.jpg","oppose_number":0},{"_id":"60766b184584dd7a3e5eb7c4","uid":103743,"courseid":20,"sectionid":5,"eid":9785,"note":"相对气流方向与飞机运动相反","updated_at":"2021-04-14 12:10:00","created_at":"2021-04-14 12:10:00","sum_number":0,"isapprove":false,"isoppose":false,"nickname":"FXZ84KGK","avatar":"http://resource.feizhiyi.com/fzy/themes/default/img/no-img.jpg","number":0,"oppose_number":0},{"_id":"6052fa258d93e30fa951c8a3","uid":103399,"courseid":20,"sectionid":5,"eid":9785,"note":"相对气流只平行于飞行速度","updated_at":"2021-03-18 14:58:45","created_at":"2021-03-18 14:58:45","sum_number":0,"isapprove":false,"isoppose":false,"nickname":"吴摄兼吴机","avatar":"http://resource.feizhiyi.com/fzy/Uploads/Attachment/20210311/103399_49388_small.jpg","number":0,"oppose_number":0},{"_id":"602100feca8d99752b7d382b","uid":86920,"courseid":20,"sectionid":5,"eid":9785,"note":"相对气流方向是飞机速度的反方向","updated_at":"2021-02-08 17:14:38","created_at":"2021-02-08 17:14:38","sum_number":0,"isapprove":false,"isoppose":false,"nickname":"Wean off","avatar":"http://resource.feizhiyi.com/fzy/Uploads/Attachment/20201229/86920_78713_small.jpg","number":0,"oppose_number":0},{"_id":"5ff7e35f25e6962ef47ec127","uid":90136,"courseid":20,"sectionid":5,"eid":9785,"note":"始终平行 ，方向相反","updated_at":"2021-01-08 12:45:27","created_at":"2021-01-08 12:45:19","sum_number":0,"isapprove":false,"isoppose":false,"nickname":"NC92A6WD","avatar":"http://resource.feizhiyi.com/fzy/themes/default/img/no-img.jpg","number":0,"oppose_number":0},{"_id":"5fdab134e6a5670f6e22e7e1","uid":98551,"courseid":20,"sectionid":5,"eid":9785,"note":"相对气流平行于飞行速度，飞机上升，则相对气流向下","updated_at":"2020-12-17 09:15:43","created_at":"2020-12-17 09:15:32","sum_number":0,"isapprove":false,"isoppose":false,"nickname":"童年的纸飞机","avatar":"http://resource.feizhiyi.com/fzy/Uploads/Attachment/20201109/98551_49364_small.jpg","number":0,"oppose_number":0},{"_id":"5fc5b464de769b1bf75fb5ae","uid":85950,"courseid":20,"sectionid":5,"eid":9785,"note":"上升相反","updated_at":"2020-12-01 11:11:32","created_at":"2020-12-01 11:11:32","sum_number":0,"isapprove":false,"isoppose":false,"nickname":"爱飞行的达达","avatar":"http://resource.feizhiyi.com/fzy/Uploads/Attachment/20210227/85950_92717_small.jpg","number":0,"oppose_number":0},{"_id":"5f957140242b2b077573dcbb","uid":97742,"courseid":20,"sectionid":5,"eid":9785,"note":"与飞机运动方向相反\n\n相对气流与飞机运动方向相反","updated_at":"2020-11-13 13:07:00","created_at":"2020-10-25 20:36:16","sum_number":0,"isapprove":false,"isoppose":false,"nickname":"TXT","avatar":"http://resource.feizhiyi.com/fzy/themes/default/img/no-img.jpg","number":0,"oppose_number":0},{"_id":"5f9af508d7b8cd20d664ca6c","uid":92901,"courseid":20,"sectionid":5,"eid":9785,"note":"上升下降 相对气流方向和飞机运动方向相反","updated_at":"2020-10-30 00:59:52","created_at":"2020-10-30 00:59:52","sum_number":0,"isapprove":false,"isoppose":false,"nickname":"咩呀咩呀咩呀咩呀咩呀","avatar":"http://resource.feizhiyi.com/fzy/Uploads/Attachment/20201014/92901_26824_small.jpg","number":0,"oppose_number":0},{"_id":"5f87a806a224d34d111f89bb","uid":97090,"courseid":20,"sectionid":5,"eid":9785,"note":"相对气流平行于速度 方向相反","updated_at":"2020-10-15 09:38:14","created_at":"2020-10-15 09:38:14","sum_number":0,"isapprove":false,"isoppose":false,"nickname":"航大吴彦祖","avatar":"http://resource.feizhiyi.com/fzy/Uploads/Attachment/20201012/97090_16553_small.jpg","number":0,"oppose_number":0},{"_id":"5f6eebfb9dadad344b195539","uid":47857,"courseid":20,"sectionid":5,"eid":9785,"note":"气流向下","updated_at":"2020-09-26 15:21:31","created_at":"2020-09-26 15:21:31","sum_number":0,"isapprove":false,"isoppose":false,"nickname":"出题淫你可摇了我吧","avatar":"http://resource.feizhiyi.com/fzy/Uploads/Attachment/20200523/47857_59646_small.jpg","number":0,"oppose_number":0},{"_id":"5f677e809acefa327e019768","uid":94799,"courseid":20,"sectionid":5,"eid":9785,"note":"相对气流方向与飞机运动方向相反","updated_at":"2020-09-21 00:08:32","created_at":"2020-09-21 00:08:32","sum_number":0,"isapprove":false,"isoppose":false,"nickname":"NC474TU8","avatar":"http://resource.feizhiyi.com/fzy/themes/default/img/no-img.jpg","number":0,"oppose_number":0},{"_id":"5f4fb57c7412f76f513f958f","uid":92504,"courseid":20,"sectionid":5,"eid":9785,"note":"相对气流与飞机速度方向相反","updated_at":"2020-09-02 23:08:44","created_at":"2020-09-02 23:08:44","sum_number":0,"isapprove":false,"isoppose":false,"nickname":"飞院91C先生","avatar":"http://resource.feizhiyi.com/fzy/Uploads/Attachment/20200909/92504_92546_small.jpg","number":0,"oppose_number":0},{"_id":"5f0156df40fecb73b879ca70","uid":90683,"courseid":20,"sectionid":5,"eid":9785,"note":"相对气流永远平行于速度，并且和速度方向相反","updated_at":"2020-07-05 12:28:15","created_at":"2020-07-05 12:28:15","sum_number":0,"isapprove":false,"isoppose":false,"nickname":"Hha","avatar":"http://resource.feizhiyi.com/fzy/Uploads/Attachment/20200617/90683_19167_small.jpg","number":0,"oppose_number":0},{"_id":"5f00885b40fecb72f755b918","uid":85951,"courseid":20,"sectionid":5,"eid":9785,"note":"相对气流是飞机速度的反方向","updated_at":"2020-07-04 21:47:07","created_at":"2020-07-04 21:47:07","sum_number":0,"isapprove":false,"isoppose":false,"nickname":"飞院插秧王","avatar":"http://resource.feizhiyi.com/fzy/Uploads/Attachment/20200622/85951_25072_small.jpg","number":0,"oppose_number":0},{"_id":"5ee9c6ac40fecb7c266e53c3","uid":88214,"courseid":20,"sectionid":5,"eid":9785,"note":"相对气流平行与飞行速度\n方向与飞行速度相反","updated_at":"2020-06-17 15:30:52","created_at":"2020-06-17 15:30:52","sum_number":0,"isapprove":false,"isoppose":false,"nickname":"爱抽华子的李会长","avatar":"http://resource.feizhiyi.com/fzy/Uploads/Attachment/20200717/88214_36431_small.jpg","number":0,"oppose_number":0},{"_id":"5d89f63840fecb340b52c13f","uid":79741,"courseid":20,"sectionid":5,"eid":9785,"note":"飞机上升，气流向下","updated_at":"2019-09-24 18:55:59","created_at":"2019-09-24 18:55:52","sum_number":0,"isapprove":false,"isoppose":false,"nickname":"过儿","avatar":"http://resource.feizhiyi.com/fzy/Uploads/Attachment/20190909/79741_86448_small.jpg","number":0,"oppose_number":0},{"_id":"5d7c60c640fecb5c8632badb","uid":77692,"courseid":20,"sectionid":5,"eid":9785,"note":"平行且方向相反","updated_at":"2019-09-14 11:38:46","created_at":"2019-09-14 11:38:46","sum_number":0,"isapprove":false,"isoppose":false,"nickname":"14号必过","avatar":"http://resource.feizhiyi.com/fzy/Uploads/Attachment/20191110/77692_21056_small.jpg","number":0,"oppose_number":0},{"_id":"5d712ea640fecb6f46296808","uid":74025,"courseid":20,"sectionid":5,"eid":9785,"note":"相对气流和飞机速度方向相反","updated_at":"2019-09-05 23:49:58","created_at":"2019-09-05 23:49:58","sum_number":0,"isapprove":false,"isoppose":false,"nickname":"半泽直树","avatar":"http://resource.feizhiyi.com/fzy/Uploads/Attachment/20191008/74025_62851_small.jpg","number":0,"oppose_number":0},{"_id":"5d5e55e040fecb64ed582424","uid":75023,"courseid":20,"sectionid":5,"eid":9785,"note":"相对气流平行于飞行速度","updated_at":"2019-08-22 16:44:16","created_at":"2019-08-22 16:44:16","sum_number":0,"isapprove":false,"isoppose":false,"nickname":"艳光四射性不冷淡","avatar":"http://resource.feizhiyi.com/fzy/Uploads/Attachment/20191108/75023_39231_small.jpg","number":0,"oppose_number":0},{"_id":"5d5542c240fecb13335ef2f2","uid":74396,"courseid":20,"sectionid":5,"eid":9785,"note":"反正相对气流方向和速度平行相反就对了","updated_at":"2019-08-15 19:32:18","created_at":"2019-08-15 19:32:18","sum_number":0,"isapprove":false,"isoppose":false,"nickname":"Pudge","avatar":"http://resource.feizhiyi.com/fzy/Uploads/Attachment/20201116/74396_94583_small.jpg","number":0,"oppose_number":0},{"_id":"5d43d84d40fecb6574491b7c","uid":74624,"courseid":20,"sectionid":5,"eid":9785,"note":"上升或下降都是平行于飞行速度。 方向相反","updated_at":"2019-08-02 14:29:33","created_at":"2019-08-02 14:29:33","sum_number":0,"isapprove":false,"isoppose":false,"nickname":"仪表一次过","avatar":"http://resource.feizhiyi.com/fzy/Uploads/Attachment/20191102/74624_74946_small.jpg","number":0,"oppose_number":0},{"_id":"5d28347340fecb6ec213a196","uid":66076,"courseid":20,"sectionid":5,"eid":9785,"note":"点错","updated_at":"2019-07-12 15:19:15","created_at":"2019-07-12 15:19:15","sum_number":0,"isapprove":false,"isoppose":false,"nickname":"刘日天Fucksky","avatar":"http://resource.feizhiyi.com/fzy/Uploads/Attachment/20190621/66076_32025_small.jpg","number":0,"oppose_number":0},{"_id":"5d06f4e240fecb0a4c59ef92","uid":78059,"courseid":20,"sectionid":5,"eid":9785,"note":"方向向下","updated_at":"2019-06-17 10:03:14","created_at":"2019-06-17 10:03:14","sum_number":0,"isapprove":false,"isoppose":false,"nickname":"@","avatar":"http://resource.feizhiyi.com/fzy/Uploads/Attachment/20190616/78059_32444_small.jpg","number":0,"oppose_number":0},{"_id":"5c50ff1940fecb4ddf132d89","uid":64186,"courseid":20,"sectionid":5,"eid":9785,"note":"相对气流方向与飞行速度方向相反","updated_at":"2019-01-30 09:34:17","created_at":"2019-01-30 09:34:17","sum_number":0,"isapprove":false,"isoppose":false,"nickname":"Fighting","avatar":"http://resource.feizhiyi.com/fzy/Uploads/Attachment/20181010/64186_small.jpg","number":0,"oppose_number":0},{"_id":"5baa853140fecb2def15f684","uid":62879,"courseid":20,"sectionid":5,"eid":9785,"note":"相对气流 上升：下降 \n下降：上升","updated_at":"2018-09-26 02:57:53","created_at":"2018-09-26 02:57:53","sum_number":0,"isapprove":false,"isoppose":false,"nickname":"J_sir","avatar":"http://resource.feizhiyi.com/fzy/Uploads/Attachment/20180625/62879_small.jpg","number":0,"oppose_number":0},{"_id":"5b768eba40fecb5482279db8","uid":64107,"courseid":20,"sectionid":5,"eid":9785,"note":"方向向下\n\n飞机上升，相对气流向下","updated_at":"2018-09-10 16:21:36","created_at":"2018-08-17 17:00:42","sum_number":0,"isapprove":false,"isoppose":false,"nickname":"NCZ5MBQQ","avatar":"http://resource.feizhiyi.com/fzy/themes/default/img/no-img.jpg","number":0,"oppose_number":0},{"_id":"5b373a4240fecb6e9e7a7fcb","uid":61416,"courseid":20,"sectionid":5,"eid":9785,"note":"相对气流  上升向下  下降向上","updated_at":"2018-06-30 16:07:30","created_at":"2018-06-30 16:07:30","sum_number":0,"isapprove":false,"isoppose":false,"nickname":"Low","avatar":"http://resource.feizhiyi.com/fzy/Uploads/Attachment/20180527/61416_small.jpg","number":0,"oppose_number":0},{"_id":"5a74b5a740fecb1d493ab0eb","uid":44350,"courseid":20,"sectionid":5,"eid":9785,"note":"相对气流，上升下降，下降上升","created_at":"2017-08-03 14:21:30","updated_at":"2017-08-03 14:21:45","sum_number":0,"isapprove":false,"isoppose":false,"nickname":"米开朗","avatar":"http://resource.feizhiyi.com/fzy/Uploads/Attachment/20181126/44350_small.jpg","number":0,"oppose_number":0},{"_id":"5a74b5a040fecb1d4939665d","uid":40713,"courseid":20,"sectionid":5,"eid":9785,"note":"相对气流方向是向下，仔细读题！","created_at":"2017-05-12 18:22:28","updated_at":"2017-05-12 18:22:28","sum_number":0,"isapprove":false,"isoppose":false,"nickname":"NCD2CW7","avatar":"http://resource.feizhiyi.com/fzy/themes/default/img/no-img.jpg","number":0,"oppose_number":0},{"_id":"5a74b59740fecb1d4937972f","uid":38765,"courseid":20,"sectionid":5,"eid":9785,"note":"上升向下  下降向上","created_at":"2017-01-03 20:27:33","updated_at":"2017-01-03 20:27:33","sum_number":0,"isapprove":false,"isoppose":false,"nickname":"猎鹿人Calvin","avatar":"http://resource.feizhiyi.com/fzy/Uploads/Attachment/20161220/38765_small.jpg","number":0,"oppose_number":0},{"_id":"5a74b58e40fecb1d4935bb91","uid":34614,"courseid":20,"sectionid":5,"eid":9785,"note":"上升时相对气流向下","created_at":"2016-09-10 15:50:17","updated_at":"2016-09-10 15:50:17","sum_number":0,"isapprove":false,"isoppose":false,"nickname":"Forever_ ℡","avatar":"http://resource.feizhiyi.com/fzy/Uploads/Attachment/20171119/34614_small.jpg","number":0,"oppose_number":0},{"_id":"5a74b58c40fecb1d49357279","uid":36284,"courseid":20,"sectionid":5,"eid":9785,"note":"啪啪","created_at":"2016-08-29 11:09:11","updated_at":"2016-08-29 11:09:11","sum_number":0,"isapprove":false,"isoppose":false,"nickname":"PHilo","avatar":"http://resource.feizhiyi.com/fzy/Uploads/Attachment/20171218/36284_small.jpg","number":0,"oppose_number":0}],"total":36}}